RVC3/__init__.py
RVC3/bin/__init__.py
RVC3/bin/bdsim_path.py
RVC3/bin/rvctool.py
RVC3/examples/__init__.py
RVC3/examples/imu_data.py
RVC3/examples/mosaic.py
RVC3/examples/ransac_line.py
RVC3/examples/visodom.py
RVC3/examples/walking.py
RVC3/examples/writing.py
RVC3/examples/hershey/genhershey.py
RVC3/examples/hershey/hershey.json
RVC3/examples/hershey/hershey.txt
RVC3/examples/hershey/roman-plain.txt
RVC3/examples/hershey/roman-simplex.txt
RVC3/examples/hershey/roman-triplex.txt
RVC3/models/IBVS-arm-main.py
RVC3/models/IBVS-arm.bd
RVC3/models/IBVS-holonomic-main.py
RVC3/models/IBVS-holonomic.bd
RVC3/models/IBVS-main.py
RVC3/models/IBVS-nonholonomic-main.py
RVC3/models/IBVS-nonholonomic.bd
RVC3/models/IBVS-partitioned-main.py
RVC3/models/IBVS-partitioned.bd
RVC3/models/IBVS-quadrotor-main.py
RVC3/models/IBVS-quadrotor.bd
RVC3/models/IBVS.bd
RVC3/models/RRMC.bd
RVC3/models/RRMC.py
RVC3/models/RRMC2.bd
RVC3/models/RRMC2.py
RVC3/models/SEA-main.py
RVC3/models/SEA.bd
RVC3/models/SEA.py
RVC3/models/__init__.py
RVC3/models/braitenberg.bd
RVC3/models/braitenberg.py
RVC3/models/cartspace.bd
RVC3/models/computed-torque-main.py
RVC3/models/computed-torque.bd
RVC3/models/driveconfig.bd
RVC3/models/driveconfig.py
RVC3/models/driveline.bd
RVC3/models/driveline.py
RVC3/models/drivepoint.bd
RVC3/models/drivepoint.py
RVC3/models/drivepursuit.bd
RVC3/models/drivepursuit.py
RVC3/models/feedforward-main.py
RVC3/models/feedforward.bd
RVC3/models/jointspace.bd
RVC3/models/jointspace.py
RVC3/models/lanechange.bd
RVC3/models/lanechange.py
RVC3/models/opspace-main.py
RVC3/models/opspace.bd
RVC3/models/opspace.py
RVC3/models/ploop.bd
RVC3/models/ploop.py
RVC3/models/ploop_test.bd
RVC3/models/ploop_test.py
RVC3/models/quad_model.py
RVC3/models/quadrotor-main.py
RVC3/models/quadrotor.bd
RVC3/models/quadrotor.py
RVC3/models/vloop.bd
RVC3/models/vloop.py
RVC3/models/vloop_test.bd
RVC3/models/vloop_test.py
RVC3/models/zerotorque.bd
RVC3/models/zerotorque.py
RVC3/tools/__init__.py
rvc3python-0.9.2.dist-info/LICENSE
rvc3python-0.9.2.dist-info/METADATA
rvc3python-0.9.2.dist-info/WHEEL
rvc3python-0.9.2.dist-info/entry_points.txt
rvc3python-0.9.2.dist-info/top_level.txt
rvc3python-0.9.2.dist-info/RECORD
