Metadata-Version: 2.1
Name: rvc3python
Version: 0.9.2
Summary: Support for book: Robotics, Vision & Control 3 in Python
Author-email: Peter Corke <rvc@petercorke.com>
Project-URL: Homepage, https://github.com/petercorke/RVC3-python
Project-URL: Bug Tracker, https://github.com/petercorke/RVC3-python/issues
Project-URL: Source, https://github.com/petercorke/RVC3-python
Keywords: robotics,robot,manipulator,robot arm,mobile robot,mobile manipulation,path planning,SLAM,pose graph,Dubins,Reeds-Shepp,lattice planner,RRT,PRM,rapidly exploring random tree,probabilistic roadmap planner,force control,kinematics,Jacobian,position control,velocity control,spatial math,SO(2),SE(2),SO(3),SE(3),twist,product of exponential,translation,orientation,angle-axis,Lie group,skew symmetric matrix,pose,translation,rotation matrix,rigid body transform,homogeneous transformation,Euler
Classifier: Development Status :: 5 - Production/Stable
Classifier: Intended Audience :: Developers
Classifier: Programming Language :: Python :: 3.7
Classifier: Programming Language :: Python :: 3.8
Classifier: Programming Language :: Python :: 3.9
Classifier: Programming Language :: Python :: 3.10
Classifier: Programming Language :: Python :: 3.11
Classifier: Programming Language :: Python :: 3.12
Classifier: License :: OSI Approved :: MIT License
Classifier: Operating System :: OS Independent
Requires-Python: >=3.7
License-File: LICENSE
Requires-Dist: matplotlib
Requires-Dist: numpy <2
Requires-Dist: roboticstoolbox-python >=1
Requires-Dist: machinevision-toolbox-python
Requires-Dist: bdsim >=1.1
Requires-Dist: IPython
Requires-Dist: sympy
Requires-Dist: pybullet
Provides-Extra: pytorch
Requires-Dist: torch ; extra == 'pytorch'
Requires-Dist: torchvision ; extra == 'pytorch'
